setup.py
gk_distributions/Binomialdistribution.py
gk_distributions/Gaussiandistribution.py
gk_distributions/Generaldistribution.py
gk_distributions/__init__.py
gk_distributions.egg-info/PKG-INFO
gk_distributions.egg-info/SOURCES.txt
gk_distributions.egg-info/dependency_links.txt
gk_distributions.egg-info/not-zip-safe
gk_distributions.egg-info/top_level.txt