Metadata-Version: 1.0
Name: gk-distributions
Version: 0.1
Summary: Gaussian and Binomial distributions
Home-page: UNKNOWN
Author: Karthic Gunasekaran
Author-email: myemail@something.com
License: UNKNOWN
Platform: UNKNOWN
